elasticsearch_bundle/__init__.py
elasticsearch_bundle/bundle.py
elasticsearch_bundle-1.1.dist-info/DESCRIPTION.rst
elasticsearch_bundle-1.1.dist-info/METADATA
elasticsearch_bundle-1.1.dist-info/RECORD
elasticsearch_bundle-1.1.dist-info/WHEEL
elasticsearch_bundle-1.1.dist-info/metadata.json
elasticsearch_bundle-1.1.dist-info/top_level.txt
