Metadata-Version: 2.0
Name: elasticsearch-bundle
Version: 1.1
Summary: Elasticsearch support for applauncher
Home-page: https://github.com/applauncher-team/elasticsearch_bundle
Author: Alvaro Garcia Gomez
Author-email: maxpowel@gmail.com
License: UNKNOWN
Download-URL: https://github.com/applauncher-team/elasticsearch_bundle
Keywords: elasticsearch
Platform: UNKNOWN
Classifier: Topic :: Adaptive Technologies
Classifier: Topic :: Software Development
Classifier: Topic :: System
Classifier: Topic :: Utilities
Requires-Dist: elasticsearch
Requires-Dist: requests-aws4auth
